MANIFEST.in
setup.py
huchengzhen/__init__.py
huchengzhen/handson-ml2-master.zip
huchengzhen/myfunction.py
huchengzhen.egg-info/PKG-INFO
huchengzhen.egg-info/SOURCES.txt
huchengzhen.egg-info/dependency_links.txt
huchengzhen.egg-info/top_level.txt