Metadata-Version: 1.0
Name: huchengzhen
Version: 0.0.4
Summary: test pip module
Home-page: https://huchengzhen.com
Author: Hu Chengzhen
Author-email: huchengzhen@gmail.com
License: MIT
Keywords: pip,testpypi
Platform: any
